lazy_crawler/__init__.py
lazy_crawler/scrapy.cfg
lazy_crawler/version.py
lazy_crawler/app/auth.py
lazy_crawler/app/config.py
lazy_crawler/app/limiter.py
lazy_crawler/app/main.py
lazy_crawler/app/database/__init__.py
lazy_crawler/app/database/db.py
lazy_crawler/app/database/models.py
lazy_crawler/app/routers/__init__.py
lazy_crawler/app/routers/admin.py
lazy_crawler/app/routers/auth.py
lazy_crawler/app/routers/contact.py
lazy_crawler/app/routers/data.py
lazy_crawler/app/routers/ds.py
lazy_crawler/app/routers/health.py
lazy_crawler/app/routers/pages.py
lazy_crawler/app/services/email_service.py
lazy_crawler/app/services/ollama_service.py
lazy_crawler/app/static/cookies.css
lazy_crawler/app/static/cookies.js
lazy_crawler/app/static/dashboard.js
lazy_crawler/app/static/robots.txt
lazy_crawler/app/static/sitemap.xml
lazy_crawler/app/static/style.css
lazy_crawler/app/templates/about.html
lazy_crawler/app/templates/admin_contacts.html
lazy_crawler/app/templates/base.html
lazy_crawler/app/templates/company.html
lazy_crawler/app/templates/contact.html
lazy_crawler/app/templates/dashboard.html
lazy_crawler/app/templates/faq.html
lazy_crawler/app/templates/index.html
lazy_crawler/app/templates/login.html
lazy_crawler/app/templates/privacy.html
lazy_crawler/app/templates/register.html
lazy_crawler/app/templates/includes/cookie_consent.html
lazy_crawler/crawler/__init__.py
lazy_crawler/crawler/http.py
lazy_crawler/crawler/items.py
lazy_crawler/crawler/middlewares.py
lazy_crawler/crawler/pipelines.py
lazy_crawler/crawler/proxymiddleware.py
lazy_crawler/crawler/settings.py
lazy_crawler/crawler/spiders/__init__.py
lazy_crawler/crawler/spiders/base_crawler.py
lazy_crawler/lib/__init__.py
lazy_crawler/lib/cleaner.py
lazy_crawler/lib/date.py
lazy_crawler/lib/forms.py
lazy_crawler/lib/html.py
lazy_crawler/lib/image.py
lazy_crawler/lib/loader.py
lazy_crawler/lib/mylogger.py
lazy_crawler/lib/params.py
lazy_crawler/lib/parser.py
lazy_crawler/lib/playwright_proxy.py
lazy_crawler-2.0.1.dist-info/METADATA
lazy_crawler-2.0.1.dist-info/WHEEL
lazy_crawler-2.0.1.dist-info/licenses/LICENSE
lazy_crawler-2.0.1.dist-info/RECORD
