Metadata-Version: 2.4
Name: lazy-crawler
Version: 2.0.1
Summary: A powerful and extensible web crawling framework built with Scrapy and Playwright.
Project-URL: Homepage, https://github.com/Pradip-p/lazy-py-crawler
Author-email: Pradip Thapa <thapapradip542@gmail.com>
License: MIT
License-File: LICENSE
Requires-Python: >=3.10
Requires-Dist: aiosmtplib==5.0.0
Requires-Dist: alembic==1.17.2
Requires-Dist: asyncpg==0.31.0
Requires-Dist: bcrypt==3.2.2
Requires-Dist: brotli>=1.2.0
Requires-Dist: fastapi==0.111.0
Requires-Dist: google-auth-oauthlib==1.2.3
Requires-Dist: gspread==6.1.2
Requires-Dist: httpx==0.28.1
Requires-Dist: ipdb==0.13.13
Requires-Dist: itsdangerous==2.2.0
Requires-Dist: oauth2client==4.1.3
Requires-Dist: openpyxl==3.1.3
Requires-Dist: pandas==2.2.2
Requires-Dist: passlib[bcrypt]==1.7.4
Requires-Dist: pdfminer-six==20231228
Requires-Dist: pillow==10.3.0
Requires-Dist: playwright==1.44.0
Requires-Dist: protobuf==5.27.0
Requires-Dist: pydantic[email]==2.12.5
Requires-Dist: pymongo==4.7.2
Requires-Dist: python-dotenv==1.0.1
Requires-Dist: python-jose[cryptography]==3.5.0
Requires-Dist: pyyaml==6.0.1
Requires-Dist: ruamel-yaml==0.18.6
Requires-Dist: s3transfer==0.10.1
Requires-Dist: scrapy-playwright==0.0.35
Requires-Dist: scrapy>=2.13.4
Requires-Dist: slowapi==0.1.9
Requires-Dist: sqlmodel==0.0.30
Requires-Dist: uvicorn==0.30.1
